icon/__init__.py
icon-0.0.5.dist-info/LICENSE
icon-0.0.5.dist-info/WHEEL
icon-0.0.5.dist-info/METADATA
icon-0.0.5.dist-info/RECORD
