Metadata-Version: 2.1
Name: icon
Version: 0.0.5
Summary: Random choice from Google Material Icons in Jupyter notebook
Home-page: https://github.com/SaitoTsutomu/icon
License: MIT
Author: SaitoTsutomu
Author-email: tsutomu7@hotmail.co.jp
Requires-Python: >=3.7,<4.0
Classifier: Development Status :: 1 - Planning
Classifier: License :: OSI Approved :: MIT License
Classifier: Programming Language :: Python
Classifier: Programming Language :: Python :: 3
Classifier: Programming Language :: Python :: 3.7
Classifier: Programming Language :: Python :: 3.8
Classifier: Programming Language :: Python :: 3.9
Classifier: Topic :: Scientific/Engineering
Classifier: Topic :: Software Development
